botdash/Client.py
botdash/__init__.py
botdash/lib/__init__.py
botdash/lib/value.py
botdash.py_dev-1.0.2.dist-info/LICENSE
botdash.py_dev-1.0.2.dist-info/METADATA
botdash.py_dev-1.0.2.dist-info/WHEEL
botdash.py_dev-1.0.2.dist-info/top_level.txt
botdash.py_dev-1.0.2.dist-info/RECORD
