Metadata-Version: 2.1
Name: botdash.py-dev
Version: 1.0.2
Summary: API wrapper for botdash.pro
Home-page: https://github.com/jetnox/botdash-py
Download-URL: https://github.com/jetnox/botdash-py/tarball/master
Author: Jetnox
Author-email: support@jetnox.org
License: MIT
Keywords: botdash,discord,bot
License-File: LICENSE
Requires-Dist: setuptools
Requires-Dist: requests
Requires-Dist: six
Requires-Dist: ujson
Requires-Dist: python-socketio
